{"count":60898,"links":{"following":231171},"assets":{"totalCount":1979064,"EVM+":{"AVAX.NFT":4641,"Arbitrum.NFT":4773,"BSC.NFT":242072,"Ethereum.NFT":367804,"Polygon.NFT":521847,"xDai.POAP":787182,"FTM.NFT":8907,"Gitcoin.Donation":18529,"Mirror.XYZ":23309}},"accounts":{"EVM+":61027,"Twitter":2913,"Jike":1396,"Misskey":570,"Solana":1},"items":{"totalCount":4200048,"Arbitrum.NFT":22346,"AVAX.NFT":14906,"BSC.NFT":1106601,"Ethereum.NFT":934040,"FTM.NFT":28606,"Gitcoin.Donation":22783,"Jike":19742,"Mirror.XYZ":29256,"Misskey":11734,"Polygon.NFT":875983,"Twitter":311464,"xDai.POAP":822587}}