{"count":60961,"links":{"following":231331},"assets":{"totalCount":2035951,"EVM+":{"AVAX.NFT":4795,"Arbitrum.NFT":5261,"BSC.NFT":244407,"Ethereum.NFT":371155,"Polygon.NFT":529035,"xDai.POAP":828303,"FTM.NFT":9218,"Gitcoin.Donation":19519,"Mirror.XYZ":24258}},"accounts":{"EVM+":61095,"Twitter":2913,"Jike":1398,"Misskey":570,"Solana":1},"items":{"totalCount":4288900,"Arbitrum.NFT":23319,"AVAX.NFT":15221,"BSC.NFT":1115294,"Ethereum.NFT":943001,"FTM.NFT":29247,"Gitcoin.Donation":24017,"Jike":20312,"Mirror.XYZ":30427,"Misskey":12090,"Polygon.NFT":887192,"Twitter":321620,"xDai.POAP":867160}}