{"count":77168,"links":{"following":237472},"assets":{"totalCount":2457019,"EVM+":{"AVAX.NFT":7468,"Arbitrum.NFT":14465,"BSC.NFT":291967,"Ethereum.NFT":429879,"Polygon.NFT":718440,"xDai.POAP":924348,"FTM.NFT":15353,"Gitcoin.Donation":22036,"Mirror.XYZ":33063}},"accounts":{"EVM+":77358,"Twitter":3017,"Jike":1434,"Misskey":575,"Solana":1},"items":{"totalCount":5281904,"Arbitrum.NFT":41361,"AVAX.NFT":22070,"BSC.NFT":1273064,"Ethereum.NFT":1089933,"FTM.NFT":40706,"Gitcoin.Donation":27364,"Jike":29116,"Mirror.XYZ":42097,"Misskey":21591,"Polygon.NFT":1205529,"Twitter":482410,"xDai.POAP":1006663}}