{"count":77268,"links":{"following":237524},"assets":{"totalCount":2462254,"EVM+":{"AVAX.NFT":7476,"Arbitrum.NFT":15481,"BSC.NFT":292281,"Ethereum.NFT":430609,"Polygon.NFT":719974,"xDai.POAP":925586,"FTM.NFT":15353,"Gitcoin.Donation":22112,"Mirror.XYZ":33382}},"accounts":{"EVM+":77458,"Twitter":3020,"Jike":1434,"Misskey":576,"Solana":1},"items":{"totalCount":5295033,"Arbitrum.NFT":42932,"AVAX.NFT":22087,"BSC.NFT":1273382,"Ethereum.NFT":1090582,"FTM.NFT":40707,"Gitcoin.Donation":27517,"Jike":29594,"Mirror.XYZ":42674,"Misskey":21899,"Polygon.NFT":1206628,"Twitter":488494,"xDai.POAP":1008537}}