{"count":70845,"links":{"following":236689},"assets":{"totalCount":2174834,"EVM+":{"AVAX.NFT":6107,"Arbitrum.NFT":5696,"BSC.NFT":254424,"Ethereum.NFT":382285,"Polygon.NFT":562890,"xDai.POAP":902165,"FTM.NFT":11567,"Gitcoin.Donation":21306,"Mirror.XYZ":28394}},"accounts":{"EVM+":70992,"Twitter":2971,"Jike":1409,"Misskey":571,"Solana":1},"items":{"totalCount":4533595,"Arbitrum.NFT":25428,"AVAX.NFT":17748,"BSC.NFT":1130002,"Ethereum.NFT":961421,"FTM.NFT":33076,"Gitcoin.Donation":26312,"Jike":23693,"Mirror.XYZ":35209,"Misskey":15404,"Polygon.NFT":925480,"Twitter":387993,"xDai.POAP":951829}}