{"count":70699,"links":{"following":236664},"assets":{"totalCount":2173843,"EVM+":{"AVAX.NFT":6082,"Arbitrum.NFT":5696,"BSC.NFT":254219,"Ethereum.NFT":382162,"Polygon.NFT":562276,"xDai.POAP":902165,"FTM.NFT":11543,"Gitcoin.Donation":21306,"Mirror.XYZ":28394}},"accounts":{"EVM+":70846,"Twitter":2971,"Jike":1409,"Misskey":571,"Solana":1},"items":{"totalCount":4531899,"Arbitrum.NFT":25428,"AVAX.NFT":17665,"BSC.NFT":1129591,"Ethereum.NFT":961222,"FTM.NFT":32978,"Gitcoin.Donation":26312,"Jike":23693,"Mirror.XYZ":35209,"Misskey":15404,"Polygon.NFT":924575,"Twitter":387993,"xDai.POAP":951829}}