{"count":77585,"links":{"following":237764},"assets":{"totalCount":2476190,"EVM+":{"AVAX.NFT":7483,"Arbitrum.NFT":21060,"BSC.NFT":292764,"Ethereum.NFT":430885,"Polygon.NFT":720476,"xDai.POAP":930376,"FTM.NFT":15357,"Gitcoin.Donation":23285,"Mirror.XYZ":34504}},"accounts":{"EVM+":77785,"Twitter":3028,"Jike":1435,"Misskey":576,"Solana":1},"items":{"totalCount":5349225,"Arbitrum.NFT":52897,"AVAX.NFT":22087,"BSC.NFT":1273382,"Ethereum.NFT":1090582,"FTM.NFT":40707,"Gitcoin.Donation":29112,"Jike":30649,"Mirror.XYZ":44573,"Misskey":23344,"Polygon.NFT":1206628,"Twitter":515753,"xDai.POAP":1019511}}