{"count":76261,"links":{"following":237023},"assets":{"totalCount":2278329,"EVM+":{"AVAX.NFT":6667,"Arbitrum.NFT":13495,"BSC.NFT":268642,"Ethereum.NFT":394728,"Polygon.NFT":603811,"xDai.POAP":924923,"FTM.NFT":13144,"Gitcoin.Donation":21934,"Mirror.XYZ":30985}},"accounts":{"EVM+":76434,"Twitter":2987,"Jike":1421,"Misskey":573,"Solana":1},"items":{"totalCount":4790882,"Arbitrum.NFT":37607,"AVAX.NFT":19340,"BSC.NFT":1178504,"Ethereum.NFT":994864,"FTM.NFT":36112,"Gitcoin.Donation":27111,"Jike":26286,"Mirror.XYZ":38721,"Misskey":18644,"Polygon.NFT":996337,"Twitter":434051,"xDai.POAP":983305}}