{"count":76567,"links":{"following":237250},"assets":{"totalCount":2379004,"EVM+":{"AVAX.NFT":6983,"Arbitrum.NFT":13786,"BSC.NFT":283295,"Ethereum.NFT":413920,"Polygon.NFT":662966,"xDai.POAP":929640,"FTM.NFT":14674,"Gitcoin.Donation":21940,"Mirror.XYZ":31800}},"accounts":{"EVM+":76748,"Twitter":2998,"Jike":1425,"Misskey":574,"Solana":1},"items":{"totalCount":5007637,"Arbitrum.NFT":39290,"AVAX.NFT":20315,"BSC.NFT":1229105,"Ethereum.NFT":1044978,"FTM.NFT":37624,"Gitcoin.Donation":27208,"Jike":27678,"Mirror.XYZ":39802,"Misskey":19763,"Polygon.NFT":1071924,"Twitter":456169,"xDai.POAP":993781}}