{"count":67179,"links":{"following":232415},"assets":{"totalCount":2145795,"EVM+":{"AVAX.NFT":5842,"Arbitrum.NFT":5637,"BSC.NFT":250844,"Ethereum.NFT":378883,"Polygon.NFT":551998,"xDai.POAP":892929,"FTM.NFT":11097,"Gitcoin.Donation":20908,"Mirror.XYZ":27657}},"accounts":{"EVM+":67326,"Twitter":2936,"Jike":1405,"Misskey":571,"Solana":1},"items":{"totalCount":4470846,"Arbitrum.NFT":24989,"AVAX.NFT":17065,"BSC.NFT":1124445,"Ethereum.NFT":955009,"FTM.NFT":32178,"Gitcoin.Donation":25839,"Jike":22862,"Mirror.XYZ":34036,"Misskey":14265,"Polygon.NFT":911547,"Twitter":369439,"xDai.POAP":939172}}