{"count":74010,"links":{"following":236942},"assets":{"totalCount":2259379,"EVM+":{"AVAX.NFT":6559,"Arbitrum.NFT":13349,"BSC.NFT":265812,"Ethereum.NFT":391571,"Polygon.NFT":594443,"xDai.POAP":922147,"FTM.NFT":12895,"Gitcoin.Donation":21907,"Mirror.XYZ":30696}},"accounts":{"EVM+":74171,"Twitter":2985,"Jike":1421,"Misskey":572,"Solana":1},"items":{"totalCount":4725065,"Arbitrum.NFT":34731,"AVAX.NFT":19061,"BSC.NFT":1161904,"Ethereum.NFT":985301,"FTM.NFT":35418,"Gitcoin.Donation":27011,"Jike":25801,"Mirror.XYZ":38250,"Misskey":17397,"Polygon.NFT":976960,"Twitter":426694,"xDai.POAP":976537}}