{"count":76289,"links":{"following":237040},"assets":{"totalCount":2284464,"EVM+":{"AVAX.NFT":6684,"Arbitrum.NFT":13508,"BSC.NFT":269973,"Ethereum.NFT":395829,"Polygon.NFT":607062,"xDai.POAP":925265,"FTM.NFT":13174,"Gitcoin.Donation":21934,"Mirror.XYZ":31035}},"accounts":{"EVM+":76462,"Twitter":2987,"Jike":1423,"Misskey":573,"Solana":1},"items":{"totalCount":4804612,"Arbitrum.NFT":37700,"AVAX.NFT":19383,"BSC.NFT":1182471,"Ethereum.NFT":997181,"FTM.NFT":36174,"Gitcoin.Donation":27118,"Jike":26358,"Mirror.XYZ":38806,"Misskey":18668,"Polygon.NFT":1000623,"Twitter":435344,"xDai.POAP":984786}}