{"count":60880,"links":{"following":231163},"assets":{"totalCount":1974309,"EVM+":{"AVAX.NFT":4598,"Arbitrum.NFT":4756,"BSC.NFT":241671,"Ethereum.NFT":367314,"Polygon.NFT":520159,"xDai.POAP":785228,"FTM.NFT":8840,"Gitcoin.Donation":18512,"Mirror.XYZ":23231}},"accounts":{"EVM+":61009,"Twitter":2911,"Jike":1395,"Misskey":570,"Solana":1},"items":{"totalCount":4192277,"Arbitrum.NFT":22315,"AVAX.NFT":14774,"BSC.NFT":1105635,"Ethereum.NFT":933137,"FTM.NFT":28407,"Gitcoin.Donation":22763,"Jike":19635,"Mirror.XYZ":29165,"Misskey":11606,"Polygon.NFT":873025,"Twitter":310729,"xDai.POAP":821086}}