{"count":71093,"links":{"following":236857},"assets":{"totalCount":2230193,"EVM+":{"AVAX.NFT":6422,"Arbitrum.NFT":9907,"BSC.NFT":262595,"Ethereum.NFT":388221,"Polygon.NFT":585125,"xDai.POAP":913979,"FTM.NFT":12649,"Gitcoin.Donation":21587,"Mirror.XYZ":29708}},"accounts":{"EVM+":71252,"Twitter":2981,"Jike":1418,"Misskey":572,"Solana":1},"items":{"totalCount":4652214,"Arbitrum.NFT":31128,"AVAX.NFT":18783,"BSC.NFT":1151464,"Ethereum.NFT":975447,"FTM.NFT":34843,"Gitcoin.Donation":26658,"Jike":24850,"Mirror.XYZ":37043,"Misskey":16805,"Polygon.NFT":957675,"Twitter":411503,"xDai.POAP":966015}}